test0408.v
module voter_if (I, O);
input [3:0] I; // I 4 men
output [3:1] O; // O Result
reg [3:1] O;

always @(I)

case (I)
    4'b0000||4'b0001||4'b0010||4'b0100||4'b1000:
        O[3:1] = 3'b100;
    4'b0011||4'b0101||4'b0110||4'b1001||4'b1010||4'b1100:
        O[3:1] = 3'b010;
    4'b1110||4'b1101|| 4'b1011 || 4'b0111 ||4'b1111:
        O[3:1] =3'b001;
    default: O[3:1] =3'b000;
endcase
endmodule

test0408_tb.v
module voter_if_tb;
reg [3:0] I_tb;
wire  [3:1] O_tb;
voter_if voter_1(.I(I_tb),.O(O_tb));
initial
begin
    #160 $finish;
end
initial
begin
    #0   I_tb = 4'b0000;
    #10  I_tb = 4'b0001;
    #10  I_tb = 4'b0010;
    #10  I_tb = 4'b0011;
    #10  I_tb = 4'b0100;
    #10  I_tb = 4'b0101;
    #10  I_tb = 4'b0110;
    #10  I_tb = 4'b0111;
    #10  I_tb = 4'b1000;
    #10  I_tb = 4'b1001;
    #10  I_tb = 4'b1010;
    #10  I_tb = 4'b1011;
    #10  I_tb = 4'b1100;
    #10  I_tb = 4'b1101;
    #10  I_tb = 4'b1110;
    #10  I_tb = 4'b1111;
end
initial
begin
    $dumpfile("test0408.vcd");
    $dumpvars(0, voter_1);
end
endmodule

test0408.vcd
$date
	Sat Apr 16 22:54:37 2022
$end
$version
	Icarus Verilog
$end
$timescale
	1s
$end
$scope module voter_if_tb $end
$scope module voter_1 $end
$var wire 4 ! I [3:0] $end
$var reg 3 " O [3:1] $end
$upscope $end
$upscope $end
$enddefinitions $end
#0
$dumpvars
b0 "
b0 !
$end
#10
b100 "
b1 !
#20
b0 "
b10 !
#30
b11 !
#40
b100 !
#50
b101 !
#60
b110 !
#70
b111 !
#80
b1000 !
#90
b1001 !
#100
b1010 !
#110
b1011 !
#120
b1100 !
#130
b1101 !
#140
b1110 !
#150
b1111 !
